{"id": "pixel", "path": "e:\\PythonProjects\\AutomateTheBoringStuff_2e\\chapter19\\pixel.py", "mtime": 1586088409, "size": 391, "hash": "8b62875bc577eaff9bdcb088d50a34da99b2505c0ed947484278e2933d98a105", "data_mtime": 1586088407, "dependencies": ["builtins", "abc", "typing"], "suppressed": ["PIL"], "options": {"plugins": [], "warn_return_any": false, "allow_untyped_globals": false, "strict_equality": false, "platform": "win32", "disallow_incomplete_defs": false, "disallow_subclassing_any": false, "follow_imports": "silent", "strict_optional": true, "show_none_errors": true, "ignore_missing_imports": true, "warn_unreachable": false, "disallow_any_explicit": false, "always_false": [], "warn_no_return": true, "mypyc": false, "disallow_any_expr": false, "allow_redefinition": false, "local_partial_types": false, "no_implicit_optional": false, "bazel": false, "ignore_errors": false, "follow_imports_for_stubs": false, "implicit_reexport": true, "strict_optional_whitelist": null, "warn_unused_ignores": false, "disallow_untyped_decorators": false, "disallow_any_unimported": false, "always_true": [], "disallow_untyped_calls": false, "disallow_untyped_defs": false, "disallow_any_generics": false, "disallow_any_decorated": false, "check_untyped_defs": false}, "dep_prios": [5, 30, 30, 5], "dep_lines": [1, 1, 1, 1], "interface_hash": "f33295ae7b3a3b928d30fa8970fe3794bc4bccd94f767876a6fd76ab42ba64a2", "version_id": "0.770", "ignore_all": false, "plugin_data": null}